bibos_utils/__init__.py
bibos_utils/bibos_config.py
bibos_utils-0.0.3.1.data/scripts/get_bibos_config
bibos_utils-0.0.3.1.data/scripts/get_package_data
bibos_utils-0.0.3.1.data/scripts/set_bibos_config
bibos_utils-0.0.3.1.dist-info/DESCRIPTION.rst
bibos_utils-0.0.3.1.dist-info/METADATA
bibos_utils-0.0.3.1.dist-info/RECORD
bibos_utils-0.0.3.1.dist-info/WHEEL
bibos_utils-0.0.3.1.dist-info/metadata.json
bibos_utils-0.0.3.1.dist-info/top_level.txt
