Metadata-Version: 2.0
Name: bibos-utils
Version: 0.0.3.1
Summary: Utilities for the BibOS system
Home-page: https://github.com/magenta-aps/
Author: Magenta ApS
Author-email: info@magenta-aps.dk
License: GPLv3
Platform: UNKNOWN
Classifier: Development Status :: 2 - Pre-Alpha
Classifier: Operating System :: POSIX :: Linux
Classifier: Programming Language :: Python :: 2.7
Requires-Dist: PyYAML
